pmeter/__init__.py
pmeter/pmeter_cli.py
pmeter/helpers/__init__.py
pmeter/helpers/constants.py
pmeter/helpers/file_writer.py
pmeter_ods-1.2.6.dist-info/METADATA
pmeter_ods-1.2.6.dist-info/WHEEL
pmeter_ods-1.2.6.dist-info/entry_points.txt
pmeter_ods-1.2.6.dist-info/top_level.txt
pmeter_ods-1.2.6.dist-info/RECORD
