Metadata-Version: 2.4
Name: pmeter_ods
Version: 1.2.6
Summary: A CLI tool that helps capture metrics from the Operating System
Home-page: https://github.com/didclab/pmeter
Author: OneDataShare
Author-email: onedatashare@gmail.com
Classifier: Programming Language :: Python :: 3
Classifier: License :: OSI Approved :: MIT License
Classifier: Operating System :: OS Independent
Requires-Python: >=3.7
Requires-Dist: docopt
Requires-Dist: psutil
Requires-Dist: tcp-latency
Requires-Dist: ipping
Requires-Dist: pyping
Requires-Dist: py-cpuinfo
Requires-Dist: pythonping
Requires-Dist: py3-validate-email
Requires-Dist: requests
Requires-Dist: pandas
Requires-Dist: scapy
Dynamic: author
Dynamic: author-email
Dynamic: classifier
Dynamic: description
Dynamic: description-content-type
Dynamic: home-page
Dynamic: requires-dist
Dynamic: requires-python
Dynamic: summary
